<?xml version="1.0" encoding="UTF-8"?>

<beans xmlns="http://www.springframework.org/schema/beans"
       xmlns:xsi="http://www.w3.org/2001/XMLSchema-instance"
       xsi:schemaLocation="http://www.springframework.org/schema/beans http://www.springframework.org/schema/beans/spring-beans-3.0.xsd"
       xmlns:p="http://www.springframework.org/schema/p"
        >

	<!-- DAO -->
    <bean id="forms.formDAO" class="fr.paris.lutece.plugins.forms.business.FormDAO" />
    <bean id="forms.stepDAO" class="fr.paris.lutece.plugins.forms.business.StepDAO" />
    <bean id="forms.transitionDAO" class="fr.paris.lutece.plugins.forms.business.TransitionDAO" />
    <bean id="forms.questionDAO" class="fr.paris.lutece.plugins.forms.business.QuestionDAO" />
    <bean id="forms.groupDAO" class="fr.paris.lutece.plugins.forms.business.GroupDAO" />
    <bean id="forms.formActionDAO"  class="fr.paris.lutece.plugins.forms.business.FormActionDAO" />
    <bean id="forms.globalFormsActionDAO"  class="fr.paris.lutece.plugins.forms.business.action.GlobalFormsActionDAO" />
    <bean id="forms.formDisplayDAO" class="fr.paris.lutece.plugins.forms.business.FormDisplayDAO" />
    <bean id="forms.formListDAO" class="fr.paris.lutece.plugins.forms.business.form.list.FormListLuceneDAO" />
    <bean id="forms.formQuestionResponseDAO" class="fr.paris.lutece.plugins.forms.business.FormQuestionResponseDAO" />
    <bean id="forms.formResponseDAO" class="fr.paris.lutece.plugins.forms.business.FormResponseDAO" />
    <bean id="forms.formResponseStepDAO" class="fr.paris.lutece.plugins.forms.business.FormResponseStepDAO" />
    <bean id="forms.controlDAO" class="fr.paris.lutece.plugins.forms.business.ControlDAO" />
    <bean id="forms.formMessageDAO" class="fr.paris.lutece.plugins.forms.business.FormMessageDAO" />
    <bean id="forms.indexerActionDAO" class="fr.paris.lutece.plugins.forms.business.form.search.IndexerActionDAO" />
    
    <!-- Export -->
    <bean id="forms.csvExport" class="fr.paris.lutece.plugins.forms.export.csv.CSVExport">
    	<constructor-arg type="java.lang.String" index="0" value="forms.csvExport" />
    	<constructor-arg type="java.lang.String" index="1" value="forms.export.csv.name" />
        <constructor-arg type="java.lang.String" index="2" value="forms.export.csv.description" />
    </bean>
    
    <bean id="forms.pdfExport" class="fr.paris.lutece.plugins.forms.export.pdf.PDFExport">
        <constructor-arg type="java.lang.String" index="0" value="forms.pdfExport" />
        <constructor-arg type="java.lang.String" index="1" value="forms.export.pdf.name" />
        <constructor-arg type="java.lang.String" index="2" value="forms.export.pdf.description" />
    </bean>
    
    <bean id="forms.fullExport" class="fr.paris.lutece.plugins.forms.export.pdffull.PdfFullExport">
        <constructor-arg type="java.lang.String" index="0" value="forms.fullExport" />
        <constructor-arg type="java.lang.String" index="1" value="forms.export.pdffull.name" />
        <constructor-arg type="java.lang.String" index="2" value="forms.export.pdffull.description" />
    </bean>
    
    <!-- Listener services -->
    <bean id="forms.formRemovalService" class="fr.paris.lutece.portal.service.util.RemovalListenerService" />
    <bean id="forms.questionRemovalService" class="fr.paris.lutece.portal.service.util.RemovalListenerService" />
    <bean id="forms.formResponseEventListener" class="fr.paris.lutece.plugins.forms.service.listener.FormResponseEventListener" />
    <bean id="forms.listQuestionListener"
		class="fr.paris.lutece.plugins.forms.validation.ListQuestionListener" />
    
    <!-- Validator -->
    <bean id="forms.patternValidator" class="fr.paris.lutece.plugins.forms.validation.PatternValidator">
    	<constructor-arg type="java.lang.String" index="0" value="forms.patternValidator" />
    	<constructor-arg type="java.lang.String" index="1" value="forms.validator.pattern.name" />
		<constructor-arg index="2" >
			<list>
				<value type="java.lang.String">forms.entryTypeText</value>
				<value type="java.lang.String">forms.entryTypeTextArea</value>
				<value type="java.lang.String">forms.entryTypeGeolocation</value>
			</list>
		</constructor-arg>
	</bean>
	<bean id="forms.patternFileTypeValidator" class="fr.paris.lutece.plugins.forms.validation.PatternFileTypeValidator">
    	<constructor-arg type="java.lang.String" index="0" value="forms.patternFileTypeValidator" />
    	<constructor-arg type="java.lang.String" index="1" value="forms.validator.pattern.file.type.name" />
		<constructor-arg index="2" >
			<list>
				<value type="java.lang.String">forms.entryTypeFile</value>
				<value type="java.lang.String">forms.entryTypeImage</value>
				<value type="java.lang.String">forms.entryTypeAutomaticFileReading</value>
			</list>
		</constructor-arg>
	</bean>
	<bean id="forms.listValueValidator" class="fr.paris.lutece.plugins.forms.validation.ListValueValidator">
		<constructor-arg  type="java.lang.String" index="0" value="forms.listValueValidator" />
		<constructor-arg type="java.lang.String" index="1" value="forms.validator.listValue.name" />
		<constructor-arg index="2" >
			<list>
				<value type="java.lang.String">forms.entryTypeCheckBox</value>
				<value type="java.lang.String">forms.entryTypeRadioButton</value>
				<value type="java.lang.String">forms.entryTypeSelect</value>
			</list>
		</constructor-arg>
	</bean>
	<bean id="forms.uniqueValidator" class="fr.paris.lutece.plugins.forms.validation.UniqueValidator">
    	<constructor-arg type="java.lang.String" index="0" value="forms.uniqueValidator" />
    	<constructor-arg type="java.lang.String" index="1" value="forms.validator.unique.name" />
		<constructor-arg index="2" >
			<list>
				<value type="java.lang.String">forms.entryTypeText</value>
				<value type="java.lang.String">forms.entryTypeMyLuteceUserattribute</value>
			
			</list>
		</constructor-arg>

	</bean>
	
	
	<!-- Breadcrumb -->
    <bean id="forms.horizontalBreadcrumb" class="fr.paris.lutece.plugins.forms.web.breadcrumb.HorizontalBreadcrumb">
    	<constructor-arg type="java.lang.String" index="0" value="forms.horizontalBreadcrumb" />
    	<constructor-arg type="java.lang.String" index="1" value="forms.breadcrumb.horizontal.name" />
	</bean>
	<bean id="forms.verticalBreadcrumb" class="fr.paris.lutece.plugins.forms.web.breadcrumb.VerticalBreadcrumb">
    	<constructor-arg type="java.lang.String" index="0" value="forms.verticalBreadcrumb" />
    	<constructor-arg type="java.lang.String" index="1" value="forms.breadcrumb.vertical.name" />
	</bean>
	
    <!-- EntryType -->
    <bean id="forms.entryTypeCheckBox" class="fr.paris.lutece.plugins.forms.service.entrytype.EntryTypeCheckBox" />
	<bean id="forms.entryTypeComment" class="fr.paris.lutece.plugins.forms.service.entrytype.EntryTypeComment" />
	<bean id="forms.entryTypeDate" class="fr.paris.lutece.plugins.forms.service.entrytype.EntryTypeDate" />
	<bean id="forms.entryTypeFile" class="fr.paris.lutece.plugins.forms.service.entrytype.EntryTypeFile" />
	<bean id="forms.entryTypeGeolocation" class="fr.paris.lutece.plugins.forms.service.entrytype.EntryTypeGeolocation" />
	<bean id="forms.entryTypeImage" class="fr.paris.lutece.plugins.forms.service.entrytype.EntryTypeImage" />
	<bean id="forms.entryTypeMyLuteceUser" class="fr.paris.lutece.plugins.forms.service.entrytype.EntryTypeMyLuteceUser" />
	<bean id="forms.entryTypeNumbering" class="fr.paris.lutece.plugins.forms.service.entrytype.EntryTypeNumbering" />
	<bean id="forms.entryTypeRadioButton" class="fr.paris.lutece.plugins.forms.service.entrytype.EntryTypeRadioButton" />
	<bean id="forms.entryTypeSelect" class="fr.paris.lutece.plugins.forms.service.entrytype.EntryTypeSelect" />
	<bean id="forms.entryTypeText" class="fr.paris.lutece.plugins.forms.service.entrytype.EntryTypeText" />
	<bean id="forms.entryTypeTextArea" class="fr.paris.lutece.plugins.forms.service.entrytype.EntryTypeTextArea" />
	<bean id="forms.entryTypeMyLuteceUserattribute" class="fr.paris.lutece.plugins.forms.service.entrytype.EntryTypeMyLuteceUserAttribute" />
	<bean id="forms.entryTypeArray" class="fr.paris.lutece.plugins.forms.service.entrytype.EntryTypeArray" />
    <bean id="forms.entryTypeTermsOfService" class="fr.paris.lutece.plugins.forms.service.entrytype.EntryTypeTermsOfService" />
    <bean id="forms.entryTypeAutomaticFileReading" class="fr.paris.lutece.plugins.forms.service.entrytype.EntryTypeAutomaticFileReading" />

	<!-- DisplayService -->
	<bean id="forms.entryTypeCheckBoxDisplayService" class="fr.paris.lutece.plugins.forms.web.entrytype.EntryTypeDefaultDisplayService">
		<constructor-arg  type="java.lang.String" value="forms.entryTypeCheckBox" />
	</bean>
	<bean id="forms.entryTypeCommentDisplayService" class="fr.paris.lutece.plugins.forms.web.entrytype.EntryTypeCommentDisplayService">
		<constructor-arg  type="java.lang.String" value="forms.entryTypeComment" />
	</bean>
	<bean id="forms.entryTypeDateDisplayService" class="fr.paris.lutece.plugins.forms.web.entrytype.EntryTypeDateDisplayService">
		<constructor-arg  type="java.lang.String" value="forms.entryTypeDate" />
	</bean>
	<bean id="forms.entryTypeFileDisplayService" class="fr.paris.lutece.plugins.forms.web.entrytype.EntryTypeFileDisplayService">
		<constructor-arg  type="java.lang.String" value="forms.entryTypeFile" />
	</bean>
	<bean id="forms.entryTypeGeolocationDisplayService" class="fr.paris.lutece.plugins.forms.web.entrytype.EntryTypeGeolocDisplayService">
		<constructor-arg  type="java.lang.String" value="forms.entryTypeGeolocation" />
	</bean>
	<bean id="forms.entryTypeImageDisplayService" class="fr.paris.lutece.plugins.forms.web.entrytype.EntryTypeFileDisplayService">
		<constructor-arg  type="java.lang.String" value="forms.entryTypeImage" />
	</bean>
	<bean id="forms.entryTypeMyLuteceUserDisplayService" class="fr.paris.lutece.plugins.forms.web.entrytype.EntryTypeDefaultDisplayService">
		<constructor-arg  type="java.lang.String" value="forms.entryTypeMyLuteceUser" />
	</bean>
	<bean id="forms.entryTypeNumberingDisplayService" class="fr.paris.lutece.plugins.forms.web.entrytype.EntryTypeDefaultDisplayService">
		<constructor-arg  type="java.lang.String" value="forms.entryTypeNumbering" />
	</bean>
	<bean id="forms.entryTypeRadioButtonDisplayService" class="fr.paris.lutece.plugins.forms.web.entrytype.EntryTypeDefaultDisplayService">
		<constructor-arg  type="java.lang.String" value="forms.entryTypeRadioButton" />
	</bean>
	<bean id="forms.entryTypeSelectDisplayService" class="fr.paris.lutece.plugins.forms.web.entrytype.EntryTypeDefaultDisplayService">
		<constructor-arg  type="java.lang.String" value="forms.entryTypeSelect" />
	</bean>
	<bean id="forms.entryTypeTextDisplayService" class="fr.paris.lutece.plugins.forms.web.entrytype.EntryTypeDefaultDisplayService">
		<constructor-arg  type="java.lang.String" value="forms.entryTypeText" />
	</bean>
	<bean id="forms.entryTypeTextAreaDisplayService" class="fr.paris.lutece.plugins.forms.web.entrytype.EntryTypeDefaultDisplayService">
		<constructor-arg  type="java.lang.String" value="forms.entryTypeTextArea" />
	</bean>
	<bean id="forms.entryTypeMyLuteceUserattributeDisplayService" class="fr.paris.lutece.plugins.forms.web.entrytype.EntryTypeMyLuteceUserAttributeDisplayService">
		<constructor-arg  type="java.lang.String" value="forms.entryTypeMyLuteceUserattribute" />
	</bean>
	<bean id="forms.entryTypeArrayDisplayService" class="fr.paris.lutece.plugins.forms.web.entrytype.EntryTypeDefaultDisplayService">
		<constructor-arg  type="java.lang.String" value="forms.entryTypeArray" />
	</bean>
    <bean id="forms.entryTypeTermsOfSerciceDisplayService" class="fr.paris.lutece.plugins.forms.web.entrytype.EntryTypeDefaultDisplayService">
        <constructor-arg  type="java.lang.String" value="forms.entryTypeTermsOfService" />
    </bean>
    <bean id="forms.entryTypeAutomaticFileReadingDisplayService" class="fr.paris.lutece.plugins.forms.web.entrytype.EntryTypeFileReadingDisplayService">
		<constructor-arg  type="java.lang.String" value="forms.entryTypeAutomaticFileReading" />
	</bean>
	
	<!-- DataService -->
	<bean id="forms.entryTypeCheckBoxDataService" class="fr.paris.lutece.plugins.forms.web.entrytype.EntryTypeIterableDataService">
		<constructor-arg  type="java.lang.String" value="forms.entryTypeCheckBox" />
	</bean>
	<bean id="forms.entryTypeCommentDataService" class="fr.paris.lutece.plugins.forms.web.entrytype.EntryTypeDefaultDataService">
		<constructor-arg  type="java.lang.String" value="forms.entryTypeComment" />
	</bean>
	<bean id="forms.entryTypeDateDataService" class="fr.paris.lutece.plugins.forms.web.entrytype.EntryTypeIterableDataService">
		<constructor-arg  type="java.lang.String" value="forms.entryTypeDate" />
	</bean>
	<bean id="forms.entryTypeFileDataService" class="fr.paris.lutece.plugins.forms.web.entrytype.EntryTypeFileDataService">
		<constructor-arg  type="java.lang.String" value="forms.entryTypeFile" />
	</bean>
	<bean id="forms.entryTypeGeolocationDataService" class="fr.paris.lutece.plugins.forms.web.entrytype.EntryTypeDefaultDataService">
		<constructor-arg  type="java.lang.String" value="forms.entryTypeGeolocation" />
	</bean>
	<bean id="forms.entryTypeGroupDataService" class="fr.paris.lutece.plugins.forms.web.entrytype.EntryTypeDefaultDataService">
		<constructor-arg  type="java.lang.String" value="forms.entryTypeGroup" />
	</bean>
	<bean id="forms.entryTypeImageDataService" class="fr.paris.lutece.plugins.forms.web.entrytype.EntryTypeFileDataService">
		<constructor-arg  type="java.lang.String" value="forms.entryTypeImage" />
	</bean>
	<bean id="forms.entryTypeMyLuteceUserDataService" class="fr.paris.lutece.plugins.forms.web.entrytype.EntryTypeDefaultDataService">
		<constructor-arg  type="java.lang.String" value="forms.entryTypeMyLuteceUser" />
	</bean>
	<bean id="forms.entryTypeNumberingDataService" class="fr.paris.lutece.plugins.forms.web.entrytype.EntryTypeDefaultDataService">
		<constructor-arg  type="java.lang.String" value="forms.entryTypeNumbering" />
	</bean>
	<bean id="forms.entryTypeRadioButtonDataService" class="fr.paris.lutece.plugins.forms.web.entrytype.EntryTypeIterableDataService">
		<constructor-arg  type="java.lang.String" value="forms.entryTypeRadioButton" />
	</bean>
	<bean id="forms.entryTypeSelectDataService" class="fr.paris.lutece.plugins.forms.web.entrytype.EntryTypeIterableDataService">
		<constructor-arg  type="java.lang.String" value="forms.entryTypeSelect" />
	</bean>
	<bean id="forms.entryTypeTextDataService" class="fr.paris.lutece.plugins.forms.web.entrytype.EntryTypeIterableDataService">
		<constructor-arg  type="java.lang.String" value="forms.entryTypeText" />
	</bean>
	<bean id="forms.entryTypeTextAreaDataService" class="fr.paris.lutece.plugins.forms.web.entrytype.EntryTypeIterableDataService">
		<constructor-arg  type="java.lang.String" value="forms.entryTypeTextArea" />
	</bean>
	<bean id="forms.entryTypeMyLuteceUserattributeDataService" class="fr.paris.lutece.plugins.forms.web.entrytype.EntryTypeIterableDataService">
		<constructor-arg  type="java.lang.String" value="forms.entryTypeMyLuteceUserattribute" />
	</bean>
	<bean id="forms.entryTypeArrayDataService" class="fr.paris.lutece.plugins.forms.web.entrytype.EntryTypeIterableDataService">
		<constructor-arg  type="java.lang.String" value="forms.entryTypeArray" />
	</bean>
    <bean id="forms.entryTypeTermsOfServiceDataService" class="fr.paris.lutece.plugins.forms.web.entrytype.EntryTypeIterableDataService">
        <constructor-arg  type="java.lang.String" value="forms.entryTypeTermsOfService" />
    </bean>
    <bean id="forms.entryTypeAutomaticFileReadingDataService" class="fr.paris.lutece.plugins.forms.web.entrytype.EntryTypeFileDataService">
		<constructor-arg  type="java.lang.String" value="forms.entryTypeAutomaticFileReading" />
	</bean>
		
	<bean id="forms.asynchronousUploadHandler" class="fr.paris.lutece.plugins.forms.service.upload.FormsAsynchronousUploadHandler" />
	
    <!-- Transaction Manager -->
    <bean id="forms.transactionManager"  class="fr.paris.lutece.portal.service.database.LuteceTransactionManager"
        p:pluginName="forms" />

    <bean id="forms.formDisplayService" class="fr.paris.lutece.plugins.forms.service.FormDisplayService" />
    <bean id="forms.stepService" class="fr.paris.lutece.plugins.forms.service.StepService" />
    <bean id="forms.formService" class="fr.paris.lutece.plugins.forms.service.FormService" />
    <bean id="forms.formWorkflowService" class="fr.paris.lutece.plugins.forms.service.workflow.FormWorkflowServiceImpl" />
    	
    <!-- Forms Multiview Authorization Service -->
    <bean id="forms.formsMultiviewAuthorizationService" class="fr.paris.lutece.plugins.forms.service.FormsMultiviewAuthorizationService">
        <constructor-arg name="formPanelConfiguration" ref="forms.formsPanel.panelConfiguration"/>
    </bean>
    
    <!-- Lucene Search services implementation -->
    <bean id="forms.luceneFormsSearchEngine" class="fr.paris.lutece.plugins.forms.service.search.LuceneFormSearchEngine"/>
    <bean id="forms.luceneFormsSearchIndexer" class="fr.paris.lutece.plugins.forms.service.search.LuceneFormSearchIndexer"/>
    <bean id="forms.luceneFormsSearchFactory" class="fr.paris.lutece.plugins.forms.service.search.LuceneFormSearchFactory" scope="singleton"/>
    <bean id="forms.luceneFrenchAnalizer" class="fr.paris.lutece.plugins.lucene.service.analyzer.LuteceFrenchAnalyzer"/>
    
	<!-- FormList Facade -->
    <bean id="forms.formList.facade" class="fr.paris.lutece.plugins.forms.business.form.list.FormListFacade">
    	<constructor-arg name="formListDAO" type="fr.paris.lutece.plugins.forms.business.form.list.IFormListDAO" ref="forms.formListDAO" />
    </bean>
    
    <!-- Factory -->
    <bean id="forms.formColumn.factory" class="fr.paris.lutece.plugins.forms.business.form.column.FormColumnFactory"/>
    
    <!-- Panels Initializer QueryParts Factories -->
    <bean id="forms.formPanelInitializer.panelForms.queryPart.factory" class="fr.paris.lutece.plugins.forms.business.form.panel.initializer.querypart.factory.impl.FormPanelFormsInitializerQueryPartFactory"/>
    <bean id="forms.formPanelInitializer.panelFormResponse.queryPart.factory" class="fr.paris.lutece.plugins.forms.business.form.panel.initializer.querypart.factory.impl.FormPanelFormResponseInitializerQueryPartFactory"/>
    
    <!-- Filters QueryParts Factories -->    
    <bean id="forms.formFilter.formResponse.queryPart.factory" class="fr.paris.lutece.plugins.forms.business.form.filter.querypart.factory.impl.FormFilterFormsQueryPartFactory"/>
    <bean id="forms.formFilter.formResponseDateCreation.queryPart.factory" class="fr.paris.lutece.plugins.forms.business.form.filter.querypart.factory.impl.FormFilterFormResponseDateQueryPartFactory"/>
    <bean id="forms.formFilter.entry.queryPart.factory" class="fr.paris.lutece.plugins.forms.business.form.filter.querypart.factory.impl.FormFilterEntryQueryPartFactory"/>
    <bean id="forms.formFilter.workflowState.queryPart.factory" class="fr.paris.lutece.plugins.forms.business.form.filter.querypart.factory.impl.FormFilterWorkflowStateQueryPartFactory"/>
    <bean id="forms.formFilter.idFormResponse.queryPart.factory" class="fr.paris.lutece.plugins.forms.business.form.filter.querypart.factory.impl.FormFilterIdFormResponseQueryPartFactory"/>
	
	<!-- Panels Configurations -->
	<bean id="forms.formsPanel.panelConfiguration" class="fr.paris.lutece.plugins.forms.business.form.panel.configuration.FormPanelConfiguration">
		<constructor-arg name="strTechnicalCode" type="java.lang.String" value="forms"/>
		<constructor-arg name="nPosition" type="int" value="1"/>
		<constructor-arg name="strTitle" type="java.lang.String" value="forms.formsPanel.panelConfiguration.title"/>
		<constructor-arg name="listFormPanelInitializerName">
			<list>
				<value type="java.lang.String">fr.paris.lutece.plugins.forms.business.form.panel.initializer.impl.FormPanelFormsInitializer</value>
				<value type="java.lang.String">fr.paris.lutece.plugins.forms.business.form.panel.initializer.impl.FormPanelFormResponseInitializer</value>
			</list>
		</constructor-arg>
	</bean>

	<!-- MultiviewMap -->
	<!-- Example configuration using module-multiviewmapleaflet or module-multiviewmapgismap
	<alias name="forms-multiviewmapleaflet.mapProvider" alias="forms.multiviewMap"/>
	<alias name="forms-multiviewmapgismap.mapProvider" alias="forms.multiviewMap"/>
	-->
	
	<!-- Filters Configurations -->
	<bean id="forms.forms.filterConfiguration" class="fr.paris.lutece.plugins.forms.business.form.filter.configuration.FormFilterFormsConfiguration">
		<constructor-arg name="nPosition" type="int" value="1"/>
		<constructor-arg name="strFormFilterLabel" type="java.lang.String" value="forms.filter.form.title"/>
		<constructor-arg name="strFormFilterName" type="java.lang.String" value="forms_title"/>
	</bean>
	<bean id="forms.formResponseDateCreation.filterConfiguration" class="fr.paris.lutece.plugins.forms.business.form.filter.configuration.FormFilterDateConfiguration">
		<constructor-arg name="nPosition" type="int" value="2"/>
		<constructor-arg name="strFormFilterLabel" type="java.lang.String" value="forms.filter.creation.title"/>
		<constructor-arg name="strFormFilterName" type="java.lang.String" value="response_creation_date"/>
	</bean>
    <bean id="forms.formResponseDateUpdate.filterConfiguration" class="fr.paris.lutece.plugins.forms.business.form.filter.configuration.FormFilterDateConfiguration">
        <constructor-arg name="nPosition" type="int" value="3"/>
        <constructor-arg name="strFormFilterLabel" type="java.lang.String" value="forms.filter.update.title"/>
        <constructor-arg name="strFormFilterName" type="java.lang.String" value="response_update_date"/>
    </bean>
    <bean id="forms.searchedText.filterConfiguration" class="fr.paris.lutece.plugins.forms.business.form.filter.configuration.FormFilterFormResponseIdConfiguration">
		<constructor-arg name="nPosition" type="int" value="4"/>
		<constructor-arg name="strFormFilterLabel" type="java.lang.String" value="forms.filter.text.title"/>
		<constructor-arg name="strFormFilterName" type="java.lang.String" value="search_text"/>
	</bean>
    <bean id="forms.workflowState.filterConfiguration" class="fr.paris.lutece.plugins.forms.business.form.filter.configuration.FormFilterWorkflowConfiguration">
		<constructor-arg name="nPosition" type="int" value="5"/>
		<constructor-arg name="strFormFilterLabel" type="java.lang.String" value="forms.filter.state.title"/>
		<constructor-arg name="strFormFilterName" type="java.lang.String" value="workflow_state"/>
	</bean>
	
	<!-- Panels Display Initializer Factories -->
	<bean id="forms.formPanelInitializer.panelForms.display.factory" class="fr.paris.lutece.plugins.forms.web.form.panel.display.initializer.factory.impl.FormPanelFormsDisplayInitializerFactory"/>
	<bean id="forms.formPanelInitializer.panelFormResponse.display.factory" class="fr.paris.lutece.plugins.forms.web.form.panel.display.initializer.factory.impl.FormPanelFormResponseDisplayInitializerFactory"/>
	
	<!-- Filters Factories -->
	<bean id="forms.formResponseDateCreation.filter.display.factory" class="fr.paris.lutece.plugins.forms.web.form.filter.display.factory.impl.FormFilterDisplayFormResponseDateFactory"/>
    <bean id="forms.formResponseDateUpdate.filter.display.factory" class="fr.paris.lutece.plugins.forms.web.form.filter.display.factory.impl.FormFilterDisplayFormResponseDateFactory"/>
	<bean id="forms.forms.filter.display.factory" class="fr.paris.lutece.plugins.forms.web.form.filter.display.factory.impl.FormFilterDisplayFormsFactory"/>
	<bean id="forms.entry.filter.display.factory" class="fr.paris.lutece.plugins.forms.web.form.filter.display.factory.impl.FormFilterDisplayEntryFactory"/>
	<bean id="forms.workflowState.filter.display.factory" class="fr.paris.lutece.plugins.forms.web.form.filter.display.factory.impl.FormFilterDisplayWorkflowStateFactory"/>
	<bean id="forms.searchedText.filter.display.factory" class="fr.paris.lutece.plugins.forms.web.form.filter.display.factory.impl.FormFilterDisplaySearchedTextFactory"/>
	
	<!-- Columns QueryPart Factories -->
	<bean id="forms.formColumn.forms.queryPart.factory" class="fr.paris.lutece.plugins.forms.business.form.column.querypart.factory.impl.FormColumnFormsQueryPartFactory"/>
	<bean id="forms.formColumn.formResponseDateCreation.queryPart.factory" class="fr.paris.lutece.plugins.forms.business.form.column.querypart.factory.impl.FormColumnFormResponseDateCreationQueryPartFactory"/>
    <bean id="forms.formColumn.formResponseDateUpdate.queryPart.factory" class="fr.paris.lutece.plugins.forms.business.form.column.querypart.factory.impl.FormColumnFormResponseDateUpdateQueryPartFactory"/>
	<bean id="forms.formColumn.entry.queryPart.factory" class="fr.paris.lutece.plugins.forms.business.form.column.querypart.factory.impl.FormColumnEntryQueryPartFactory"/>	
	<bean id="forms.formColumn.entrygeolocation.queryPart.factory" class="fr.paris.lutece.plugins.forms.business.form.column.querypart.factory.impl.FormColumnEntryGeolocationQueryPartFactory"/>
	<bean id="forms.formColumn.workflowState.queryPart.factory" class="fr.paris.lutece.plugins.forms.business.form.column.querypart.factory.impl.FormColumnWorkflowStateQueryPartFactory"/>
	
	<!-- Columns -->
	<bean id="forms.forms.column" class="fr.paris.lutece.plugins.forms.business.form.column.impl.FormColumnForms">
		<constructor-arg name="nFormColumnPosition" type="int" value="1"/>
		<constructor-arg name="strFormColumnTitle" type="java.lang.String" value="forms.column.form.title"/>
	</bean>

	<bean id="forms.formResponseCreationDate.column" class="fr.paris.lutece.plugins.forms.business.form.column.impl.FormColumnFormResponseDateCreation">
		<constructor-arg name="nFormColumnPosition" type="int" value="2"/>
		<constructor-arg name="strFormColumnTitle" type="java.lang.String" value="forms.column.creation.title"/>
	</bean>
    
    <bean id="forms.formResponseUpdateDate.column" class="fr.paris.lutece.plugins.forms.business.form.column.impl.FormColumnFormResponseDateUpdate">
        <constructor-arg name="nFormColumnPosition" type="int" value="3"/>
        <constructor-arg name="strFormColumnTitle" type="java.lang.String" value="forms.column.update.title"/>
    </bean>
    
    <bean id="forms.workflowState.column" class="fr.paris.lutece.plugins.forms.business.form.column.impl.FormColumnWorkflowState">
		<constructor-arg name="nFormColumnPosition" type="int" value="4"/>		
		<constructor-arg name="strFormColumnTitle" type="java.lang.String" value="forms.column.state.title"/>
	</bean>
	 
	<!-- Columns Factories -->
	<bean id="forms.forms.column.display.factory" class="fr.paris.lutece.plugins.forms.web.form.column.display.factory.impl.FormColumnDisplayFormsFactory"/>
	<bean id="forms.formResponseDateCreation.column.display.factory" class="fr.paris.lutece.plugins.forms.web.form.column.display.factory.impl.FormColumnDisplayFormResponseDateCreationFactory"/>
    <bean id="forms.formResponseDateUpdate.column.display.factory" class="fr.paris.lutece.plugins.forms.web.form.column.display.factory.impl.FormColumnDisplayFormResponseDateUpdateFactory"/>
	<bean id="forms.entry.column.display.factory" class="fr.paris.lutece.plugins.forms.web.form.column.display.factory.impl.FormColumnDisplayEntryFactory"/>
	<bean id="forms.entrygeolocation.column.display.factory" class="fr.paris.lutece.plugins.forms.web.form.column.display.factory.impl.FormColumnDisplayEntryGeolocationFactory"/>
	<bean id="forms.workflowState.column.display.factory" class="fr.paris.lutece.plugins.forms.web.form.column.display.factory.impl.FormColumnDisplayWorkflowStateFactory"/>
	
	<!-- Panels Display Factories -->
	<bean id="forms.panelForms.panel.display.factory" class="fr.paris.lutece.plugins.forms.web.form.panel.display.factory.impl.FormPanelFormsDisplayFactory"/>
    
    <bean id="forms.formsFileDownloadProvider" class="fr.paris.lutece.plugins.forms.service.download.FormsFileDownloadProvider"/>
</beans>
